mjpreprocessor-0.1.6.dist-info/METADATA
mjpreprocessor-0.1.6.dist-info/WHEEL
mjpreprocessor/__init__.py
mjpreprocessor/mjpreprocessor.pyd
mjpreprocessor-0.1.6.dist-info/RECORD
