Metadata-Version: 2.4
Name: mjpreprocessor
Version: 0.1.6
Classifier: Programming Language :: Python :: 3
Classifier: Programming Language :: Python :: Implementation :: CPython
Classifier: Programming Language :: Rust
Classifier: Operating System :: POSIX :: Linux
Classifier: Operating System :: Microsoft :: Windows
Classifier: Operating System :: MacOS
Summary: Fast PDF/DOCX preprocessor with Rust + PyO3
Author-email: Your Name <you@example.com>
Requires-Python: >=3.8
